{
  "tid": 59556,
  "sid": 43992,
  "target": "ho-oh",
  "base_offset": 2000,
  "nature_filter": null,
  "frame_range": [
    0,
    200000
  ],
  "total_found": 31,
  "frames": [
    {
      "frame": 187265,
      "pid": "C51A8663",
      "nature": "Mild",
      "ivs": {
        "hp": 30,
        "atk": 30,
        "def": 7,
        "spa": 28,
        "spd": 30,
        "spe": 26
      }
    },
    {
      "frame": 109950,
      "pid": "018942F3",
      "nature": "Serious",
      "ivs": {
        "hp": 25,
        "atk": 21,
        "def": 21,
        "spa": 20,
        "spd": 31,
        "spe": 27
      }
    },
    {
      "frame": 160340,
      "pid": "15E85695",
      "nature": "Adamant",
      "ivs": {
        "hp": 16,
        "atk": 28,
        "def": 27,
        "spa": 20,
        "spd": 18,
        "spe": 28
      }
    },
    {
      "frame": 194859,
      "pid": "6F302C49",
      "nature": "Mild",
      "ivs": {
        "hp": 16,
        "atk": 27,
        "def": 19,
        "spa": 31,
        "spd": 17,
        "spe": 18
      }
    },
    {
      "frame": 173971,
      "pid": "28A86BD2",
      "nature": "Modest",
      "ivs": {
        "hp": 18,
        "atk": 11,
        "def": 17,
        "spa": 17,
        "spd": 31,
        "spe": 30
      }
    },
    {
      "frame": 10957,
      "pid": "7EA03DDA",
      "nature": "Timid",
      "ivs": {
        "hp": 13,
        "atk": 28,
        "def": 23,
        "spa": 19,
        "spd": 13,
        "spe": 27
      }
    },
    {
      "frame": 196705,
      "pid": "59CF1AB4",
      "nature": "Serious",
      "ivs": {
        "hp": 30,
        "atk": 10,
        "def": 30,
        "spa": 21,
        "spd": 13,
        "spe": 16
      }
    },
    {
      "frame": 53812,
      "pid": "BA5BF922",
      "nature": "Bold",
      "ivs": {
        "hp": 5,
        "atk": 31,
        "def": 8,
        "spa": 26,
        "spd": 20,
        "spe": 27
      }
    },
    {
      "frame": 78908,
      "pid": "AD07EE7B",
      "nature": "Gentle",
      "ivs": {
        "hp": 3,
        "atk": 25,
        "def": 27,
        "spa": 31,
        "spd": 18,
        "spe": 5
      }
    },
    {
      "frame": 58284,
      "pid": "2A3F6940",
      "nature": "Lax",
      "ivs": {
        "hp": 21,
        "atk": 18,
        "def": 14,
        "spa": 6,
        "spd": 19,
        "spe": 28
      }
    },
    {
      "frame": 171730,
      "pid": "9F75DC0D",
      "nature": "Naive",
      "ivs": {
        "hp": 1,
        "atk": 31,
        "def": 17,
        "spa": 6,
        "spd": 20,
        "spe": 28
      }
    },
    {
      "frame": 151242,
      "pid": "5075130D",
      "nature": "Rash",
      "ivs": {
        "hp": 17,
        "atk": 11,
        "def": 3,
        "spa": 25,
        "spd": 18,
        "spe": 27
      }
    },
    {
      "frame": 25139,
      "pid": "1A525928",
      "nature": "Quiet",
      "ivs": {
        "hp": 13,
        "atk": 2,
        "def": 29,
        "spa": 22,
        "spd": 6,
        "spe": 28
      }
    },
    {
      "frame": 130778,
      "pid": "C99F8AE2",
      "nature": "Rash",
      "ivs": {
        "hp": 5,
        "atk": 18,
        "def": 22,
        "spa": 9,
        "spd": 15,
        "spe": 30
      }
    },
    {
      "frame": 178139,
      "pid": "4727045B",
      "nature": "Bold",
      "ivs": {
        "hp": 11,
        "atk": 18,
        "def": 5,
        "spa": 21,
        "spd": 20,
        "spe": 24
      }
    },
    {
      "frame": 84581,
      "pid": "1326505C",
      "nature": "Rash",
      "ivs": {
        "hp": 5,
        "atk": 7,
        "def": 28,
        "spa": 25,
        "spd": 5,
        "spe": 28
      }
    },
    {
      "frame": 68143,
      "pid": "B1C8F2B5",
      "nature": "Modest",
      "ivs": {
        "hp": 28,
        "atk": 25,
        "def": 0,
        "spa": 13,
        "spd": 5,
        "spe": 25
      }
    },
    {
      "frame": 157428,
      "pid": "E2D5A1AA",
      "nature": "Calm",
      "ivs": {
        "hp": 19,
        "atk": 17,
        "def": 23,
        "spa": 14,
        "spd": 2,
        "spe": 19
      }
    },
    {
      "frame": 107424,
      "pid": "76C635B8",
      "nature": "Bashful",
      "ivs": {
        "hp": 15,
        "atk": 0,
        "def": 28,
        "spa": 21,
        "spd": 7,
        "spe": 22
      }
    },
    {
      "frame": 151724,
      "pid": "9991DAE9",
      "nature": "Lax",
      "ivs": {
        "hp": 14,
        "atk": 5,
        "def": 24,
        "spa": 19,
        "spd": 13,
        "spe": 17
      }
    },
    {
      "frame": 41016,
      "pid": "E81FAB61",
      "nature": "Lonely",
      "ivs": {
        "hp": 7,
        "atk": 24,
        "def": 19,
        "spa": 9,
        "spd": 29,
        "spe": 3
      }
    },
    {
      "frame": 183198,
      "pid": "6037234C",
      "nature": "Brave",
      "ivs": {
        "hp": 19,
        "atk": 8,
        "def": 30,
        "spa": 15,
        "spd": 1,
        "spe": 14
      }
    },
    {
      "frame": 55041,
      "pid": "FFFCBC80",
      "nature": "Impish",
      "ivs": {
        "hp": 8,
        "atk": 23,
        "def": 19,
        "spa": 15,
        "spd": 7,
        "spe": 14
      }
    },
    {
      "frame": 146975,
      "pid": "8DA5CED8",
      "nature": "Careful",
      "ivs": {
        "hp": 27,
        "atk": 6,
        "def": 28,
        "spa": 19,
        "spd": 0,
        "spe": 1
      }
    },
    {
      "frame": 19261,
      "pid": "FB82B8FE",
      "nature": "Naughty",
      "ivs": {
        "hp": 21,
        "atk": 18,
        "def": 16,
        "spa": 5,
        "spd": 12,
        "spe": 5
      }
    },
    {
      "frame": 52740,
      "pid": "33A270D9",
      "nature": "Serious",
      "ivs": {
        "hp": 6,
        "atk": 18,
        "def": 16,
        "spa": 12,
        "spd": 19,
        "spe": 1
      }
    },
    {
      "frame": 103001,
      "pid": "4A77090B",
      "nature": "Impish",
      "ivs": {
        "hp": 29,
        "atk": 16,
        "def": 3,
        "spa": 2,
        "spd": 19,
        "spe": 2
      }
    },
    {
      "frame": 173220,
      "pid": "3EEF7D93",
      "nature": "Bashful",
      "ivs": {
        "hp": 12,
        "atk": 8,
        "def": 29,
        "spa": 1,
        "spd": 4,
        "spe": 15
      }
    },
    {
      "frame": 175730,
      "pid": "FF31BC49",
      "nature": "Calm",
      "ivs": {
        "hp": 17,
        "atk": 6,
        "def": 9,
        "spa": 8,
        "spd": 14,
        "spe": 14
      }
    },
    {
      "frame": 42418,
      "pid": "35D976A6",
      "nature": "Lax",
      "ivs": {
        "hp": 6,
        "atk": 17,
        "def": 8,
        "spa": 8,
        "spd": 11,
        "spe": 1
      }
    },
    {
      "frame": 142352,
      "pid": "ABB5E8C9",
      "nature": "Calm",
      "ivs": {
        "hp": 7,
        "atk": 7,
        "def": 18,
        "spa": 9,
        "spd": 3,
        "spe": 7
      }
    }
  ]
}